vmware_nsxlib/__init__.py
vmware_nsxlib/_i18n.py
vmware_nsxlib/version.py
vmware_nsxlib/tests/__init__.py
vmware_nsxlib/tests/base.py
vmware_nsxlib/tests/unit/__init__.py
vmware_nsxlib/tests/unit/v3/__init__.py
vmware_nsxlib/tests/unit/v3/mocks.py
vmware_nsxlib/tests/unit/v3/nsxlib_testcase.py
vmware_nsxlib/tests/unit/v3/test_cert.py
vmware_nsxlib/tests/unit/v3/test_client.py
vmware_nsxlib/tests/unit/v3/test_cluster.py
vmware_nsxlib/tests/unit/v3/test_cluster_management.py
vmware_nsxlib/tests/unit/v3/test_constants.py
vmware_nsxlib/tests/unit/v3/test_load_balancer.py
vmware_nsxlib/tests/unit/v3/test_native_dhcp.py
vmware_nsxlib/tests/unit/v3/test_ns_group_manager.py
vmware_nsxlib/tests/unit/v3/test_qos_switching_profile.py
vmware_nsxlib/tests/unit/v3/test_resources.py
vmware_nsxlib/tests/unit/v3/test_router.py
vmware_nsxlib/tests/unit/v3/test_security.py
vmware_nsxlib/tests/unit/v3/test_trust_management.py
vmware_nsxlib/tests/unit/v3/test_utils.py
vmware_nsxlib/tests/unit/v3/test_vpn_ipsec.py
vmware_nsxlib/tests/unit/v3/policy/__init__.py
vmware_nsxlib/tests/unit/v3/policy/policy_testcase.py
vmware_nsxlib/tests/unit/v3/policy/test_alb_auth_token_provider.py
vmware_nsxlib/tests/unit/v3/policy/test_api.py
vmware_nsxlib/tests/unit/v3/policy/test_ipsec_vpn_resources.py
vmware_nsxlib/tests/unit/v3/policy/test_lb_resources.py
vmware_nsxlib/tests/unit/v3/policy/test_resources.py
vmware_nsxlib/tests/unit/v3/policy/test_transaction.py
vmware_nsxlib/v3/__init__.py
vmware_nsxlib/v3/client.py
vmware_nsxlib/v3/client_cert.py
vmware_nsxlib/v3/cluster.py
vmware_nsxlib/v3/cluster_management.py
vmware_nsxlib/v3/config.py
vmware_nsxlib/v3/constants.py
vmware_nsxlib/v3/core_resources.py
vmware_nsxlib/v3/debug_retry.py
vmware_nsxlib/v3/exceptions.py
vmware_nsxlib/v3/lib.py
vmware_nsxlib/v3/load_balancer.py
vmware_nsxlib/v3/native_dhcp.py
vmware_nsxlib/v3/ns_group_manager.py
vmware_nsxlib/v3/nsx_constants.py
vmware_nsxlib/v3/resources.py
vmware_nsxlib/v3/router.py
vmware_nsxlib-19.4.3.dist-info/AUTHORS
vmware_nsxlib-19.4.3.dist-info/LICENSE
vmware_nsxlib-19.4.3.dist-info/METADATA
vmware_nsxlib-19.4.3.dist-info/WHEEL
vmware_nsxlib-19.4.3.dist-info/pbr.json
vmware_nsxlib-19.4.3.dist-info/top_level.txt
vmware_nsxlib-19.4.3.dist-info/RECORD
