Metadata-Version: 2.1
Name: vmware-nsxlib
Version: 19.4.3
Summary: A common library that interfaces with VMware NSX
Home-page: https://opendev.org/x/vmware-nsxlib
Author: OpenStack
Author-email: openstack-discuss@lists.openstack.org
License: UNKNOWN
Platform: UNKNOWN
Classifier: Environment :: OpenStack
Classifier: Intended Audience :: Information Technology
Classifier: Intended Audience :: System Administrators
Classifier: License :: OSI Approved :: Apache Software License
Classifier: Operating System :: POSIX :: Linux
Classifier: Programming Language :: Python
Classifier: Programming Language :: Python :: 3
Classifier: Programming Language :: Python :: 3.6
Classifier: Programming Language :: Python :: 3.7
Requires-Dist: cryptography
Requires-Dist: decorator (>=4.4.1)
Requires-Dist: eventlet (>=0.24.1)
Requires-Dist: netaddr (>=0.7.18)
Requires-Dist: oslo.i18n (>=3.20.0)
Requires-Dist: oslo.serialization (>=2.28.1)
Requires-Dist: oslo.service (>=1.31.0)
Requires-Dist: oslo.utils (>=4.4.0)
Requires-Dist: pbr (>=4.0.0)
Requires-Dist: pyOpenSSL (>=20.0.0)
Requires-Dist: tenacity (>=6.0.0)
Requires-Dist: oslo.log (>=4.2.1) ; (python_version=='3.6')
Requires-Dist: oslo.log (>=4.2.1) ; (python_version=='3.7')
Requires-Dist: oslo.log (>=5.0.0) ; (python_version=='3.8')
